[{"AmountIntermediantPoints":1,"Displacement":"3.1944444444444441528e-08"},{"AmountIntermediantPoints":2,"Displacement":"3.1944444444444620199e-08"},{"AmountIntermediantPoints":4,"Displacement":"3.1944444444444745931e-08"},{"AmountIntermediantPoints":8,"Displacement":"3.1944444444422670135e-08"},{"AmountIntermediantPoints":16,"Displacement":"3.1944444444593889904e-08"},{"AmountIntermediantPoints":32,"Displacement":"3.1944444446457236656e-08"},{"AmountIntermediantPoints":64,"Displacement":"3.1944444360170936614e-08"},{"AmountIntermediantPoints":128,"Displacement":"3.1944444243177647444e-08"},{"AmountIntermediantPoints":256,"Displacement":"3.1944450490141745214e-08"},{"AmountIntermediantPoints":512,"Displacement":"3.1944443028966948835e-08"},{"AmountIntermediantPoints":1024,"Displacement":"3.1944479679492366618e-08"},{"AmountIntermediantPoints":2048,"Displacement":"3.1890456059410576052e-08"},{"AmountIntermediantPoints":4096,"Displacement":"3.1953158285008765037e-08"},{"AmountIntermediantPoints":8192,"Displacement":"3.1741887094506080800e-08"},{"AmountIntermediantPoints":16384,"Displacement":"1.0577813960774907509e-08"},{"AmountIntermediantPoints":32768,"Displacement":"1.1624343452954322152e-09"},{"AmountIntermediantPoints":65536,"Displacement":"1.5518124772441089521e-10"},{"AmountIntermediantPoints":131072,"Displacement":"1.9371357389056466816e-11"},{"AmountIntermediantPoints":262144,"Displacement":"-1.9552898800699844207e-12"}]